wavelength/__init__.py
wavelength/calculate.py
wavelength/wavelength.py
wave_length-1.3.dist-info/METADATA
wave_length-1.3.dist-info/WHEEL
wave_length-1.3.dist-info/entry_points.txt
wave_length-1.3.dist-info/top_level.txt
wave_length-1.3.dist-info/RECORD
