Metadata-Version: 2.1
Name: wave-length
Version: 1.3
Summary: 使用步长为0.1 nm 的标准CIE色度匹配图进行光谱波长计算
Home-page: https://github.com/royallucky/
Author: LiuBing
Author-email: 2577082896@qq.com
Maintainer: LiuBing
Maintainer-email: 2577082896@qq.com
License: MIT License
Platform: UNKNOWN
Classifier: Development Status :: 3 - Alpha
Classifier: Intended Audience :: Developers
Classifier: Topic :: Software Development :: Build Tools
Classifier: License :: OSI Approved :: MIT License
Classifier: Programming Language :: Python :: 3
Requires-Python: >=3.6
Requires-Dist: numpy
Requires-Dist: pandas
Requires-Dist: matplotlib
